xitorch/__init__.py
xitorch/_core/__init__.py
xitorch/_core/editable_module.py
xitorch/_core/linop.py
xitorch/_core/packer.py
xitorch/_core/pure_function.py
xitorch/_docstr/__init__.py
xitorch/_docstr/api_docstr.py
xitorch/_impls/README.md
xitorch/_impls/__init__.py
xitorch/_impls/integrate/__init__.py
xitorch/_impls/integrate/fixed_quad.py
xitorch/_impls/integrate/ivp/__init__.py
xitorch/_impls/integrate/ivp/adaptive_rk.py
xitorch/_impls/integrate/ivp/explicit_rk.py
xitorch/_impls/integrate/mcsamples/__init__.py
xitorch/_impls/integrate/mcsamples/mcmc.py
xitorch/_impls/integrate/samples_quad.py
xitorch/_impls/interpolate/__init__.py
xitorch/_impls/interpolate/base_interp.py
xitorch/_impls/interpolate/extrap_utils.py
xitorch/_impls/interpolate/interp_1d.py
xitorch/_impls/linalg/__init__.py
xitorch/_impls/linalg/solve.py
xitorch/_impls/linalg/symeig.py
xitorch/_impls/optimize/__init__.py
xitorch/_impls/optimize/equilibrium.py
xitorch/_impls/optimize/minimizer.py
xitorch/_impls/optimize/root/__init__.py
xitorch/_impls/optimize/root/_jacobian.py
xitorch/_impls/optimize/root/rootsolver.py
xitorch/_tests/__init__.py
xitorch/_tests/test_debug.py
xitorch/_tests/test_editable_module.py
xitorch/_tests/test_integrate.py
xitorch/_tests/test_integrate_speed.py
xitorch/_tests/test_interp.py
xitorch/_tests/test_jac.py
xitorch/_tests/test_linop.py
xitorch/_tests/test_linop_fcns.py
xitorch/_tests/test_memleak.py
xitorch/_tests/test_optimize.py
xitorch/_tests/test_packer.py
xitorch/_tests/test_pure_function.py
xitorch/_tests/test_utils.py
xitorch/_tests/test_wrap_nnmodule.py
xitorch/_tests/utils.py
xitorch/_utils/__init__.py
xitorch/_utils/assertfuncs.py
xitorch/_utils/attr.py
xitorch/_utils/bcast.py
xitorch/_utils/decorators.py
xitorch/_utils/exceptions.py
xitorch/_utils/misc.py
xitorch/_utils/tensor.py
xitorch/_utils/tupleops.py
xitorch/_utils/types.py
xitorch/_utils/unique.py
xitorch/debug/__init__.py
xitorch/debug/__main__.py
xitorch/debug/modes.py
xitorch/grad/__init__.py
xitorch-0.5.1.dist-info/WHEEL
xitorch-0.5.1.dist-info/METADATA
xitorch-0.5.1.dist-info/LICENSE
xitorch-0.5.1.dist-info/RECORD
