Metadata-Version: 2.1
Name: xitorch
Version: 0.5.1
Summary: Differentiable scientific computing library
Home-page: https://xitorch.readthedocs.io/
License: MIT
Keywords: project,library,linear-algebra,autograd,functionals
Author: mfkasim1
Author-email: firman.kasim@gmail.com
Requires-Python: >=3.8.1,<3.12
Classifier: Intended Audience :: Science/Research
Classifier: License :: OSI Approved :: MIT License
Classifier: Programming Language :: Python :: 3
Classifier: Programming Language :: Python :: 3.9
Classifier: Programming Language :: Python :: 3.10
Classifier: Programming Language :: Python :: 3.11
Classifier: Programming Language :: Python :: 3.8
Classifier: Programming Language :: Python :: 3.9
Classifier: Topic :: Scientific/Engineering
Classifier: Topic :: Scientific/Engineering :: Mathematics
Classifier: Topic :: Scientific/Engineering :: Physics
Requires-Dist: numpy (>=1.24.1)
Requires-Dist: scipy (>=1.10.0)
Requires-Dist: torch (>=1.13.1)
Project-URL: Repository, https://github.com/xitorch/xitorch/tree/master/
